[
	{ "id": "MESSAGE TYPE IDENTIFICATION 1", "start": 1, "end": 4 },
	{ "id": "PRIMARY BIT MAP", "start": 5, "end": 20 },
	{ "id": "DE(01) SECONDARY BIT MAP", "start": 21, "end": 36 },
	{ "id": "DE(02) NUMERO DE TARJETA", "start": 37, "end": 54 },
	{ "id": "DE(03) CODIGO DE PROCESO", "start": 55, "end": 60 },
	{ "id": "DE(04) MONTO", "start": 61, "end": 72 },
	{ "id": "DE(07) FECHA Y HORA DE TRANSACCION", "start": 73, "end": 82 },
	{ "id": "DE(11) TRACE", "start": 83, "end": 88 },
	{ "id": "DE(17) FECHA DE CAPTURA", "start": 89, "end": 92 },
	{ "id": "DE(22) MODO DE INGRESO DE DATOS", "start": 93, "end": 95 },
	{ "id": "DE(25) CANAL", "start": 96, "end": 97 },
	{ "id": "DE(32) BIN ADQUIRIENTE", "start": 98, "end": 105 },
	{ "id": "DE(33) FORWARD INSTITUTION CODE", "start": 106, "end": 113 },
	{ "id": "DE(37) RETRIEVAL REFERENCE -NUMBER", "start": 114, "end": 125 },
	{ "id": "DE(39) RESPONSE CODE", "start": 126, "end": 127 },
	{ "id": "DE(41) TERMINAL ID", "start": 128, "end": 135 },
	{ "id": "DE(42) COMERCIO", "start": 136, "end": 150 },
	{ "id": "DE(43) CARD ACCEPTOR LOCATION", "start": 151, "end": 190 },
	{ "id": "DE(49) TRANSACTION CURRENCY CODE", "start": 191, "end": 193 },
	{ "id": "MESSAGE TYPE IDENTIFICATION 2", "start": 194, "end": 197 },
	{ "id": "TRACE", "start": 198, "end": 203 },
	{ "id": "FECHA Y HORA DE TRANSACCION", "start": 204, "end": 213 },
	{ "id": "BIN ADQUIRIENTE", "start": 214, "end": 224 },
	{ "id": "FORWARD INSTITUTION CODE", "start": 225, "end": 235 },
	{ "id": "DE(124) DATOS RESERVADOS", "start": 236, "end": 240 },
	{ "id": "LONGITUD DE DATO", "start": 241, "end": 243 },
	{ "id": "CODIGO DE FORMATO", "start": 244, "end": 245 },
	{ "id": "BIN PROCESADOR", "start": 246, "end": 256 },
	{ "id": "CODIGO DE ACREEDOR", "start": 257, "end": 267 },
	{ "id": "CODIGO DE PRODUCTO/SERVICIO", "start": 268, "end": 275 },
	{ "id": "CODIGO DE PLAZA DEL RECAUDADOR", "start": 276, "end": 279 },
	{ "id": "CODIGO DE AGENCIA DEL RECAUDADOR", "start": 280, "end": 283 },
	{ "id": "TIPO DE DATO DE PAGO", "start": 284, "end": 285 },
	{ "id": "DATO DE PAGO", "start": 286, "end": 306 },
	{ "id": "CODIGO DE CIUDAD", "start": 307, "end": 309 },
	{ "id": "FILLER", "start": 310, "end": 321 },
	{ "id": "TIPO DE SERVICIO", "start": 322, "end": 324 },
	{ "id": "NUMERO DE DOCUMENTO", "start": 325, "end": 340 },
	{ "id": "DISPONIBLE", "start": 341, "end": 371 },
	{ "id": "NUMERO DE TRANS. DE COB.ORI", "start": 372, "end": 383 },
	{ "id": "NUMERO OPE. ORIGINAL ACREED", "start": 384, "end": 395 }
]
